backtesting_data/__init__.py
backtesting_data/history.py
backtesting_data/exchange/__init__.py
backtesting_data/exchange/binance_futures.py
backtesting_data/exchange/binance_futures_cm.py
backtesting_data/exchange/binance_spot.py
backtesting_data/exchange/bingx.py
backtesting_data-0.0.3.dist-info/LICENSE
backtesting_data-0.0.3.dist-info/METADATA
backtesting_data-0.0.3.dist-info/WHEEL
backtesting_data-0.0.3.dist-info/top_level.txt
backtesting_data-0.0.3.dist-info/RECORD
