Metadata-Version: 2.1
Name: backtesting_data
Version: 0.0.3
Summary: Libreria para obtener datos para usar en backtesting.py
Home-page: https://github.com/ferromariano/backtesting-data
Author: Mariano Damian Ferro Villanueva
Author-email: <ferro.mariano@gmail.com>
Keywords: python,backtesting.py,backtesting,exchange
Classifier: Development Status :: 3 - Alpha
Classifier: Intended Audience :: Education
Classifier: Programming Language :: Python :: 3
Classifier: Operating System :: MacOS :: MacOS X
Classifier: Operating System :: Microsoft :: Windows
License-File: LICENSE
Requires-Dist: pandas
Requires-Dist: numpy
Requires-Dist: ccxt
Requires-Dist: datetime
Requires-Dist: logging
